byu_gradescope_harness.py
byu_gradescope_harness-0.1.3.dist-info/WHEEL
byu_gradescope_harness-0.1.3.dist-info/METADATA
byu_gradescope_harness-0.1.3.dist-info/RECORD
