Metadata-Version: 2.1
Name: byu-gradescope-harness
Version: 0.1.3
Summary: A test harness for Gradescope autograding
Author: Gordon Bean
Author-email: gbean@cs.byu.edu
Requires-Python: >=3.6,<4.0
Classifier: Programming Language :: Python :: 3
Classifier: Programming Language :: Python :: 3.10
Classifier: Programming Language :: Python :: 3.6
Classifier: Programming Language :: Python :: 3.7
Classifier: Programming Language :: Python :: 3.8
Classifier: Programming Language :: Python :: 3.9
